pytektronix/__init__.py
pytektronix/command_group_objects.py
pytektronix/not_connecting.sh
pytektronix/pytektronix_base_classes.py
pytektronix/scopes.py
pytektronix-1.0.4.dist-info/METADATA
pytektronix-1.0.4.dist-info/WHEEL
pytektronix-1.0.4.dist-info/licenses/LICENSE
pytektronix-1.0.4.dist-info/RECORD
